<?xml version="1.0" encoding="UTF-8" ?>
<language lang="ua-UK">
	<entry key="LBL_DOWNLOADS">Завантаження</entry>
	<entry key="LBL_UPLOADS">Відправка</entry>
	<entry key="LBL_SEARCH">Пошук</entry>
	<entry key="LBL_FRIENDS">Друзі</entry>
	<entry key="LBL_SERVERS">Сервера</entry>
	<entry key="LBL_DO">Завантаж.:</entry>
	<entry key="LBL_UP">Відпр.:</entry>
	<entry key="LBL_AVGDO">Середнє:</entry>
	<entry key="LBL_DOWNLOADED">Завантажено</entry>
	<entry key="LBL_UPLOADED">Відправлено</entry>
	<entry key="LBL_OPTIONAL">Додатковий</entry>
	<entry key="MSG_EXIT">Ви дійсно бажаєте вийти з Hathi?</entry>
	<entry key="MSG_NEWCHAT">Нова розмова: </entry>
	<entry key="LBL_OPTIONS">Налаштування</entry>
	<entry key="LBL_CONNDISC">З'єднатися/роз'єднатися з серверами</entry>
	<entry key="LBL_USERS">Користувачі</entry>
	<entry key="LBL_FILES">Файли</entry>
	<entry key="LBL_SHOWHIDEDETAILS">Показати / приховати властивості файлу</entry>
	<entry key="LBL_PASTELINK">Вст. посилання</entry>
	<entry key="LBL_ALL">Все</entry>
	<entry key="LBL_FILTER">Фільтр:</entry>
	<entry key="LBL_ADDLINK">Дод. посилання</entry>	
	<entry key="LBL_STARTED">Розпочато</entry>	
	<entry key="LBL_STOPPED">Зупинено</entry>
	<entry key="LBL_DETAILS">Подробиці</entry>
	<entry key="LBL_COMMENTS">Коментарі</entry>
	<entry key="LBL_SETCOMMENT">Мої коментарі</entry>
	<entry key="LBL_FILCOMMENTS">Коментарі файлу:</entry>
	<entry key="LBL_RENAME">Нове им'я</entry>
	<entry key="LBL_FILENAMES">Імена файлів:</entry>
	<entry key="LBL_SOURCES">Джерела</entry>
	<entry key="LBL_CANCEL">Відміна</entry>
	<entry key="LBL_FILE">Файл</entry>
	<entry key="LBL_ADD">Додати</entry>
	<entry key="LBL_SEARCHANY">пошук будь-якого із слів</entry>
	<entry key="LBL_SEARCHEXTEND">Знайти далі</entry>
	<entry key="LBL_SEARCHFILE">Пошук</entry>
	<entry key="LBL_AVAILABILITY">Доступність</entry>
	<entry key="LBL_SIZELOWER">Розмір (MБ)</entry>
	<entry key="LBL_SIZEUPPER">Розмір (MБ)</entry>
	<entry key="LBL_ANY">Будь-який</entry>
	<entry key="LBL_IMAGE">Зображення</entry>
	<entry key="LBL_PROGRAM">Програма</entry>
	<entry key="LBL_AUDIO">Аудио</entry>
	<entry key="LBL_VIDEO">Відео</entry>
	<entry key="LBL_FILENAME">Им'я файлу</entry>
	<entry key="LBL_SIZE">Розмір</entry>			
	<entry key="LBL_SPEED">Швидкість</entry>			
	<entry key="LBL_COMPLETED">Завершено</entry>			
	<entry key="LBL_REMAINING">Залишилося</entry>			
	<entry key="LBL_USEFULLSOURCES">Залишилося пам'яті</entry>			
	<entry key="LBL_TRANSFERS">Передачі</entry>			
	<entry key="LBL_STATUS">Статус</entry>			
	<entry key="LBL_PROGRESS">Прогрес</entry>
	<entry key="LBL_PRIORITY">Приорітет</entry>			
	<entry key="LBL_START">Старт</entry>			
	<entry key="LBL_STOP">Стоп</entry>			
	<entry key="LBL_PREVIEW">Попередній перегляд</entry>			
	<entry key="LBL_OPENFILE">Відкрити файл</entry>			
	<entry key="LBL_COPYLINK">Скопіювати посилання в буфер обміну</entry>			
	<entry key="LBL_CLEARCOMPLETED">Очистити завершені</entry>	
	<entry key="LBL_READY">Готовий</entry>	
	<entry key="LBL_PAUSED">Приостановлено</entry>	
	<entry key="LBL_COMPLETE">Завершено</entry>	
	<entry key="LBL_COMPLETING">Завершння</entry>	
	<entry key="LBL_VERYLOW">Дуже повільно</entry>
	<entry key="LBL_LOW">Повільно</entry>	
	<entry key="LBL_NORMAL">Нормально</entry>	
	<entry key="LBL_HIGH">Швидко</entry>	
	<entry key="LBL_VERYHIGH">Дуже швидко</entry>
	<entry key="LBL_AUTO">Авто</entry>
	<entry key="LBL_DOWNLOAD">Завантажити</entry>
	<entry key="LBL_FILETYPE">Тип файла</entry>
	<entry key="LBL_CLEARLOG">Очистити лог</entry>
	<entry key="LBL_SERVERNAME">Им'я сервера</entry>
	<entry key="LBL_ADDRESS">Адреса</entry>
	<entry key="LBL_FAILED">Збій</entry>
	<entry key="LBL_CONNECT">З'єднатися</entry>
	<entry key="LBL_DELETE">Видалити</entry>
	<entry key="LBL_SEND">Відправити</entry>
	<entry key="LBL_SENDMESSAGE">Відправити повідомлення</entry>
	<entry key="LBL_ADDFRIEND">Додати друга</entry>
	<entry key="LBL_DELETEFRIEND">Видалити друга</entry>
	<entry key="LBL_RENAMEFRIEND">Періменувати друга</entry>
	<entry key="LBL_MYNEWFRIEND">Мій новий друг</entry>
	<entry key="LBL_SHAREDFILES">Загальні файли</entry>
	<entry key="LBL_RELOADSHAREDFILES">Змінити загальні файли</entry>
	<entry key="LBL_NAME">Ім'я</entry>
	<entry key="LBL_UPLOAD">Завантажити</entry>
	<entry key="LBL_SOFTWARE">Програмне забезпечення</entry>
	<entry key="LBL_VERSION">Версія</entry>
	<entry key="LBL_VIEWFILES">Перегляд файлів</entry>
	<entry key="LBL_POSITION">Позиція</entry>
	<entry key="LBL_USER">Користувач</entry>	
	<entry key="LBL_USERHASH">Хеш користувача</entry>	
	<entry key="LBL_RATING">Рейтинг</entry>
	<entry key="LBL_COMMENT">Коментар</entry>
	<entry key="LBL_PATH">Шлях</entry>
	<entry key="LBL_KERNEL">Ядро</entry>
	<entry key="LBL_INTERFACE">Інтерфейс</entry>
	<entry key="LBL_NICK">Нік</entry>
	<entry key="LBL_CONNECTION">Підключення</entry>
	<entry key="LBL_MAXDOWNSPEED">Макс. швидкість завантаження</entry>
	<entry key="LBL_MAXUPSPEED">Макс. швидкість відправки</entry>
	<entry key="LBL_MAXCONNECTIONS">Макс. з'єднань</entry>
	<entry key="LBL_MAXSOURCESPERFILE">Макс. джер. на файл</entry>
	<entry key="LBL_TCPPORT">TCP порт</entry>
	<entry key="LBL_UDPPORT">UDP порт</entry>
	<entry key="LBL_PORT">Порт</entry>
	<entry key="LBL_ENABLEICH">Активувати ICH</entry>
	<entry key="LBL_AUTOCONNECT">Автоз'єднання</entry>
	<entry key="LBL_REMOTECONTROL">Видалене керування</entry>
	<entry key="LBL_TEMPFOLDER">Тимчасовий каталог</entry>
	<entry key="LBL_DOWNFOLDER">Каталог для завантажень</entry>
	<entry key="LBL_EXPTEMP">Додати...</entry>
	<entry key="LBL_EXPDOWN">Додати...</entry>
	<entry key="LBL_REMOVETEMP">Видалити</entry>
	<entry key="LBL_REMOVEDOWN">Видалити</entry>
	<entry key="LBL_VIEWSHARED">Перегляд загальних файлів</entry>
	<entry key="LBL_NOBODY">Ніхто</entry>
	<entry key="LBL_DOWNSERVERLIST">Список серверів</entry>
	<entry key="LBL_DOWNSERVERMET">Завантажити server.met</entry>
	<entry key="LBL_TAKELINKS">ED2K посилання</entry>
	<entry key="LBL_ACCEPT">Застосувати</entry>
	<entry key="LBL_CONNECTIONASK">Обрати тип підключення при старті</entry>
	<entry key="LBL_MINIMIZETRAY">Сховати у трей</entry>
	<entry key="LBL_NOTIFICATIONS">Повідомлення</entry>
	<entry key="LBL_VIDEOPLAYER">Відео програвач</entry>
	<entry key="LBL_EXPPLAYER">Огляд</entry>	
	<entry key="LBL_QUEUE">Черга</entry>
	<entry key="LBL_DELETEFILE">Видалити файл</entry>
	<entry key="MSG_DELETEFILE">Видалити файл {0}</entry>
	<entry key="LBL_REQUESTS">Запити</entry>
	<entry key="LBL_PENDING">Затримка</entry>
	<entry key="LBL_DOWNLOADING">Завантаження</entry>
	<entry key="LBL_ONQUEUE">На черзі</entry>
	<entry key="LBL_CONNECTING">З'єднання</entry>
	<entry key="LBL_CONNECTING_LOWID">З'єднання з LowID</entry>
	<entry key="LBL_NONEEDEDPARTS">Немає необхідних частин</entry>
	<entry key="LBL_LOWIDTOLOWID">З'єднання LowID с LowID</entry>
	<entry key="LBL_ASKING">Запит</entry>
	<entry key="LBL_NONE">Жоден</entry>
	<entry key="LBL_UPLOADING">Відправлення</entry>
	<entry key="LBL_VIDEOINFO">Відео інфо</entry>
	<entry key="LBL_VIDEOCODEC">Кодек</entry>
	<entry key="LBL_VIDEOBITRATE">Бітрейт</entry>
	<entry key="LBL_VIDEOWIDTH">Ширина</entry>
	<entry key="LBL_VIDEOHEIGHT">Висота</entry>
	<entry key="LBL_VIDEOLENGTH">Тривалість</entry>
	<entry key="LBL_VIDEOFPS">Кадрів на секунду</entry>
	<entry key="LBL_AUDIOBITRATE">Бітрейт</entry>
	<entry key="LBL_AUDIOCHANNELS">Канали</entry>
	<entry key="LBL_AUDIOCODEC">Кодек</entry>
	<entry key="LBL_AUDIOINFO">Аудио інфо</entry>
	<entry key="LBL_AUDIOSAMPLERATE">Швидкість дискретизації</entry>
	<entry key="LBL_REMOTECONTROL_SERVER">Віддалене керування сервером</entry>
	<entry key="LBL_ENABLE_REMOTECONTROL">Дозволити</entry>
	<entry key="LBL_REMOTECONTROL_PORT">Порт віддаленого керування(TCP)</entry>
	<entry key="LBL_REMOTECONTROL_PASSWORD">Пароль віддаленого керування</entry>
	<entry key="LBL_REMOTECONTROL_CLIENT">Кліент віддаленого керування</entry>
	<entry key="LBL_START_LPHANT_LOCALLY">Запустити Hathi локально (немає віддаленого керування)</entry>
	<entry key="LBL_SELECT_CONNECTIONTYPE">Вказати тип з'єднання чи віддалений хост під час запуску Hathi</entry>
	<entry key="LBL_CONNECTREMOTE">З'єднатися з цим віддаленим хостом Hathi</entry>
	<entry key="LBL_REMOTEHOST_IP">IP віддаленого хосту</entry>
	<entry key="LBL_REMOTEHOST_PORT">Порт</entry>
	<entry key="LBL_REMOTEHOST_PASSWORD">Пароль віддаленого хосту</entry>
	<entry key="LBL_ENABLEOSIG">Активувати мережевий підпис</entry>LBL_SECONDS
	<entry key="LBL_SECONDS">секунди</entry>
	<entry key="LBL_MINUTES">хвилини</entry>
	<entry key="LBL_HOURS">години</entry>
	<entry key="LBL_SHAREDFOLDERS">Загальнодоступні каталоги</entry>
	<entry key="LBL_EXPSHARED">Огляд</entry>
	<entry key="LBL_CODEC">Кодек</entry>
	<entry key="LBL_LENGTH">Довжина</entry>
	<entry key="LBL_BITRATE">Бітрейт</entry>
	<entry key="LBL_ADDSERVER">Додати сервер</entry>
	<entry key="LBL_ELINK_FROM_BROWSER_STOPPPED">Зупинити посилання із браузера</entry>
	<entry key="LBL_DOWNLOAD_SERVERLIST">Завантажити список серверів</entry>
	<entry key="LBL_SEARCHINFO">Отримати більше відомостей</entry>
	<entry key="LBL_ABOUT">Про ...</entry>
	<entry key="LBL_LPHANTWEB">Hathi Веб</entry>
	<entry key="LBL_SUPPORT">Підтримка</entry>
	<entry key="LBL_HELP">Допомога</entry>
	<entry key="LBL_AVGDOWNLOAD">Сер. рейтинг за закачками</entry>
	<entry key="LBL_AVGUPLOAD">Сер. рейтинг за відданим</entry>
	<entry key="LBL_COMPLETEDTIME">Час завершення</entry>	
	<entry key="LBL_ESTIMATED">Приблизний</entry>		
	<entry key="LBL_OPEN">Відкрити</entry>
	<entry key="LBL_QUIT">Вихід</entry>
	<entry key="LBL_EXCLUDE">Виключити результати які містять</entry>
	<entry key="LBL_AUTOMATIC">Авто</entry>
	<entry key="LBL_SHOW_ALL_LANGUAGES">Показати всі мови</entry>
	<entry key="LBL_ENABLEIPFILTER">Активувати IP фільтр</entry>
	<entry key="LBL_FILTERSHOWCOUNT">Показати кількість файлів</entry>
	<entry key="LBL_FILTERSHOWSIZES">Показать кінцевий розмір</entry>
	<entry key="LBL_FRIENDSLOT">Товариський слот</entry>
	<entry key="LBL_AUTOSORT">Автоматично сортувати список</entry>
	<entry key="LBL_OPENFOLDER">Відкрити каталог</entry>
	<entry key="LBL_IP_OR_ID">IP чи ID</entry>
	<entry key="LBL_LANGUAGE">Мова</entry>
	<entry key="LBL_SKIN">Скін</entry>
	<entry key="LBL_BYTE">Б</entry>
	<entry key="LBL_KBYTE">кБ</entry>
	<entry key="LBL_MBYTE">МБ</entry>
	<entry key="LBL_GBYTE">ГБ</entry>
	<entry key="LBL_COMPRESSION">Метод стиснення</entry>
	<entry key="LBL_ALLOWEDIP">Дозволений IP</entry>
	<entry key="LBL_STARTSTOPPEDFILE">Запустити наступний зупинений файл по закінченню завантаження</entry>
	<entry key="LBL_NOPLAYER">Вам необхідно вказати відео плеєр в налаштуваннях, ми рекомендуємо плеєр videoLAN (www.videoLAN.org)</entry>
	<entry key="LBL_CATEGORY">Категорія</entry>
	<entry key="LBL_MANAGECATEGORIES">Керування категоріями...</entry>
	<entry key="LBL_NEWCATEGORY">Нова категорія</entry>
	<entry key="LBL_REMOVECATEGORY">Видалити категорію</entry>
	<entry key="LBL_AUTOSELECTCAT">Файли з будь-яким із цих слів в имені будуть автоматично віднесені до цієї категорії</entry>
	<entry key="LBL_COLOR">Колір</entry>
</language>